opencv_cuda/__init__.py
opencv_cuda/install_script.py
opencv_cuda-0.0.2.dist-info/METADATA
opencv_cuda-0.0.2.dist-info/WHEEL
opencv_cuda-0.0.2.dist-info/entry_points.txt
opencv_cuda-0.0.2.dist-info/top_level.txt
opencv_cuda-0.0.2.dist-info/RECORD
