Metadata-Version: 2.1
Name: opencv-cuda
Version: 0.0.2
Summary: opencv-cuda simplifies the installation of GPU-accelerated OpenCV with CUDA support for efficient image and video processing. 
Home-page: https://github.com/nuhmanpk/opencv-cuda
Author: Nuhman Pk
Author-email: nuhmanpk7@gmail.com
License: MIT
Platform: UNKNOWN
Classifier: Programming Language :: Python :: 3
Classifier: Programming Language :: Python :: 3.6
Classifier: Programming Language :: Python :: 3.7
Classifier: Programming Language :: Python :: 3.8
Classifier: Programming Language :: Python :: 3.9
Classifier: License :: OSI Approved :: MIT License
Classifier: Operating System :: OS Independent
Requires-Python: >=3.6
